workflow/Notify.tgz
workflow/__init__.py
workflow/background.py
workflow/notify.py
workflow/update.py
workflow/util.py
workflow/version
workflow/workflow.py
workflow/workflow3.py
alfred_workflow_tddschn-0.1.5.dist-info/WHEEL
alfred_workflow_tddschn-0.1.5.dist-info/METADATA
alfred_workflow_tddschn-0.1.5.dist-info/RECORD
