Metadata-Version: 2.1
Name: alfred-workflow-tddschn
Version: 0.1.5
Summary: Full-featured helper library for writing Alfred 2/3/4 workflows, with Python 3
Home-page: https://github.com/tddschn/alfred-workflow-py3
License: MIT
Keywords: alfred,workflow
Author: Xinyuan Chen
Author-email: 45612704+tddschn@users.noreply.github.com
Requires-Python: >=3.10,<4.0
Classifier: Development Status :: 5 - Production/Stable
Classifier: Intended Audience :: Developers
Classifier: License :: OSI Approved :: MIT License
Classifier: Natural Language :: English
Classifier: Operating System :: MacOS :: MacOS X
Classifier: Programming Language :: Python :: 3
Classifier: Programming Language :: Python :: 3.10
Classifier: Topic :: Software Development :: Libraries
Classifier: Topic :: Software Development :: Libraries :: Application Frameworks
Requires-Dist: requests (>=2.27.1,<3.0.0)
Requires-Dist: six (>=1.16.0,<2.0.0)
Project-URL: Bug Tracker, https://github.com/tddschn/alfred-workflow-py3/issues
Project-URL: Repository, https://github.com/tddschn/alfred-workflow-py3
